README.md
setup.cfg
setup.py
accessify/__init__.py
accessify/access.py
accessify/errors.py
accessify/interfaces.py
accessify/utils.py
accessify.egg-info/PKG-INFO
accessify.egg-info/SOURCES.txt
accessify.egg-info/dependency_links.txt
accessify.egg-info/top_level.txt
examples/__init__.py
examples/dir.py
examples/access/__init__.py
examples/access/private.py
examples/access/protected.py
examples/inheritance/__init__.py
examples/inheritance/private.py
examples/inheritance/protected.py
examples/interfaces/__init__.py
examples/interfaces/multiple.py
examples/interfaces/single_access.py
examples/interfaces/single_arguments.py
examples/interfaces/single_method.py
examples/interfaces/throws.py
tests/__init__.py
tests/conftest.py
tests/utils.py
tests/access/__init__.py
tests/access/test_private.py
tests/access/test_protected.py
tests/disable/__init__.py
tests/disable/test_disable.py
tests/inheritence/__init__.py
tests/inheritence/test_private.py
tests/interfaces/__init__.py
tests/interfaces/test_get_class_members.py
tests/interfaces/test_implements.py
tests/interfaces/test_throws.py