Metadata-Version: 2.1
Name: accessify
Version: 0.3.0
Summary: Python design kit: interfaces, declared exception throws, class members accessibility levels (private and protected methods for humans).
Home-page: https://github.com/dmytrostriletskyi/accessify
Author: Dmytro Striletskyi
Author-email: dmytro.striletskyi@gmail.com
License: MIT
Platform: UNKNOWN
Classifier: Operating System :: OS Independent
Classifier: Programming Language :: Python
Classifier: Programming Language :: Python :: 3.4
Classifier: Programming Language :: Python :: 3.5
Classifier: Programming Language :: Python :: 3.6
Classifier: Programming Language :: Python :: 3.7
Classifier: License :: OSI Approved :: MIT License
